{
  "id": "featured_categories",
  "type": "SharedSlice",
  "name": "FeaturedCategories",
  "description": "FeaturedCategories",
  "variations": [
    {
      "id": "default",
      "name": "Default",
      "docURL": "...",
      "version": "initial",
      "description": "Default",
      "imageUrl": "",
      "primary": {
        "title": {
          "type": "Text",
          "config": {
            "label": "Title",
            "placeholder": ""
          }
        }
      },
      "items": {
        "tag": {
          "type": "Link",
          "config": {
            "label": "Tag",
            "select": "document",
            "customtypes": [
              "tag"
            ]
          }
        }
      }
    }
  ]
}